Metadata-Version: 2.1
Name: version-calculation
Version: 0.0.2
Summary: uma calculadora de opreções basicas para versões
Author: issei momonge
Author-email: mggyggf@gmail.com
License: MIT License
Keywords: calculadora de versão
License-File: LICENCE
